{
"warmup blocks":0,
"properties":{
"total_energy":{
"value":[-134.65],
"error":[0],
"sigma":[1.89601]
},
"kinetic":{
"value":[47.2678],
"error":[0],
"sigma":[12.4983]
},
"potential":{
"value":[-195.708],
"error":[0],
"sigma":[12.9426]
},
"nonlocal":{
"value":[13.7907],
"error":[0],
"sigma":[15.2412]
},
"weight":{
"value":[1.03131],
"error":[0],
"sigma":[0.213961]
}
},
"independent points":inf,
"commments": [
"Warning: The estimated number of independent points is _greater_ that the points in the log file. Error bars are probably unreliable! "
]
}
<RS>
{
"warmup blocks":0,
"properties":{
"total_energy":{
"value":[-134.659],
"error":[0],
"sigma":[1.90478]
},
"kinetic":{
"value":[47.4208],
"error":[0],
"sigma":[12.4886]
},
"potential":{
"value":[-195.883],
"error":[0],
"sigma":[12.9326]
},
"nonlocal":{
"value":[13.8028],
"error":[0],
"sigma":[15.2058]
},
"weight":{
"value":[1.04159],
"error":[0],
"sigma":[0.300368]
}
},
"independent points":inf,
"commments": [
"Warning: The estimated number of independent points is _greater_ that the points in the log file. Error bars are probably unreliable! "
]
}
<RS>
{
"warmup blocks":0,
"properties":{
"total_energy":{
"value":[-134.657],
"error":[0],
"sigma":[1.91101]
},
"kinetic":{
"value":[47.5212],
"error":[0],
"sigma":[12.4649]
},
"potential":{
"value":[-195.972],
"error":[0],
"sigma":[12.9512]
},
"nonlocal":{
"value":[13.7943],
"error":[0],
"sigma":[15.1827]
},
"weight":{
"value":[1.01819],
"error":[0],
"sigma":[0.312987]
}
},
"independent points":inf,
"commments": [
"Warning: The estimated number of independent points is _greater_ that the points in the log file. Error bars are probably unreliable! "
]
}
<RS>
{
"warmup blocks":0,
"properties":{
"total_energy":{
"value":[-134.656],
"error":[0],
"sigma":[1.90841]
},
"kinetic":{
"value":[47.5748],
"error":[0],
"sigma":[12.5025]
},
"potential":{
"value":[-196.181],
"error":[0],
"sigma":[12.9627]
},
"nonlocal":{
"value":[13.9498],
"error":[0],
"sigma":[15.2589]
},
"weight":{
"value":[1.00706],
"error":[0],
"sigma":[0.318483]
}
},
"independent points":inf,
"commments": [
"Warning: The estimated number of independent points is _greater_ that the points in the log file. Error bars are probably unreliable! "
]
}
<RS>
{
"warmup blocks":0,
"properties":{
"total_energy":{
"value":[-134.659],
"error":[0],
"sigma":[1.90173]
},
"kinetic":{
"value":[47.5896],
"error":[0],
"sigma":[12.4483]
},
"potential":{
"value":[-196.066],
"error":[0],
"sigma":[12.9775]
},
"nonlocal":{
"value":[13.8164],
"error":[0],
"sigma":[15.1964]
},
"weight":{
"value":[1.00246],
"error":[0],
"sigma":[0.31922]
}
},
"independent points":inf,
"commments": [
"Warning: The estimated number of independent points is _greater_ that the points in the log file. Error bars are probably unreliable! "
]
}
<RS>
{
"warmup blocks":0,
"properties":{
"total_energy":{
"value":[-134.66],
"error":[0],
"sigma":[1.91136]
},
"kinetic":{
"value":[47.6322],
"error":[0],
"sigma":[12.4723]
},
"potential":{
"value":[-196.074],
"error":[0],
"sigma":[12.9688]
},
"nonlocal":{
"value":[13.7819],
"error":[0],
"sigma":[15.1966]
},
"weight":{
"value":[1.0025],
"error":[0],
"sigma":[0.320653]
}
},
"independent points":inf,
"commments": [
"Warning: The estimated number of independent points is _greater_ that the points in the log file. Error bars are probably unreliable! "
]
}
<RS>
{
"warmup blocks":0,
"properties":{
"total_energy":{
"value":[-134.662],
"error":[0],
"sigma":[1.91256]
},
"kinetic":{
"value":[47.585],
"error":[0],
"sigma":[12.4764]
},
"potential":{
"value":[-196.002],
"error":[0],
"sigma":[12.9685]
},
"nonlocal":{
"value":[13.7555],
"error":[0],
"sigma":[15.1876]
},
"weight":{
"value":[1.00235],
"error":[0],
"sigma":[0.32351]
}
},
"independent points":inf,
"commments": [
"Warning: The estimated number of independent points is _greater_ that the points in the log file. Error bars are probably unreliable! "
]
}
<RS>
{
"warmup blocks":0,
"properties":{
"total_energy":{
"value":[-134.665],
"error":[0],
"sigma":[1.89782]
},
"kinetic":{
"value":[47.6148],
"error":[0],
"sigma":[12.4828]
},
"potential":{
"value":[-196.055],
"error":[0],
"sigma":[12.9943]
},
"nonlocal":{
"value":[13.7753],
"error":[0],
"sigma":[15.1937]
},
"weight":{
"value":[1.00328],
"error":[0],
"sigma":[0.324232]
}
},
"independent points":inf,
"commments": [
"Warning: The estimated number of independent points is _greater_ that the points in the log file. Error bars are probably unreliable! "
]
}
<RS>
{
"warmup blocks":0,
"properties":{
"total_energy":{
"value":[-134.65],
"error":[0],
"sigma":[1.93462]
},
"kinetic":{
"value":[47.6073],
"error":[0],
"sigma":[12.5225]
},
"potential":{
"value":[-196.1],
"error":[0],
"sigma":[12.9948]
},
"nonlocal":{
"value":[13.8427],
"error":[0],
"sigma":[15.304]
},
"weight":{
"value":[0.99908],
"error":[0],
"sigma":[0.324324]
}
},
"independent points":inf,
"commments": [
"Warning: The estimated number of independent points is _greater_ that the points in the log file. Error bars are probably unreliable! "
]
}
<RS>
{
"warmup blocks":0,
"properties":{
"total_energy":{
"value":[-134.658],
"error":[0],
"sigma":[1.90369]
},
"kinetic":{
"value":[47.6764],
"error":[0],
"sigma":[12.4776]
},
"potential":{
"value":[-196.239],
"error":[0],
"sigma":[13.0079]
},
"nonlocal":{
"value":[13.9052],
"error":[0],
"sigma":[15.2468]
},
"weight":{
"value":[0.995496],
"error":[0],
"sigma":[0.322712]
}
},
"independent points":inf,
"commments": [
"Warning: The estimated number of independent points is _greater_ that the points in the log file. Error bars are probably unreliable! "
]
}
<RS>
{
"warmup blocks":0,
"properties":{
"total_energy":{
"value":[-134.65],
"error":[0],
"sigma":[1.90381]
},
"kinetic":{
"value":[47.5878],
"error":[0],
"sigma":[12.409]
},
"potential":{
"value":[-196.026],
"error":[0],
"sigma":[12.9045]
},
"nonlocal":{
"value":[13.7879],
"error":[0],
"sigma":[15.0999]
},
"weight":{
"value":[0.994375],
"error":[0],
"sigma":[0.322179]
}
},
"independent points":inf,
"commments": [
"Warning: The estimated number of independent points is _greater_ that the points in the log file. Error bars are probably unreliable! "
]
}
<RS>
{
"warmup blocks":0,
"properties":{
"total_energy":{
"value":[-134.656],
"error":[0],
"sigma":[1.90789]
},
"kinetic":{
"value":[47.5971],
"error":[0],
"sigma":[12.4899]
},
"potential":{
"value":[-196.069],
"error":[0],
"sigma":[12.9552]
},
"nonlocal":{
"value":[13.8167],
"error":[0],
"sigma":[15.2192]
},
"weight":{
"value":[0.99486],
"error":[0],
"sigma":[0.323812]
}
},
"independent points":inf,
"commments": [
"Warning: The estimated number of independent points is _greater_ that the points in the log file. Error bars are probably unreliable! "
]
}
<RS>
{
"warmup blocks":0,
"properties":{
"total_energy":{
"value":[-134.661],
"error":[0],
"sigma":[1.89467]
},
"kinetic":{
"value":[47.6087],
"error":[0],
"sigma":[12.4766]
},
"potential":{
"value":[-196.071],
"error":[0],
"sigma":[12.9425]
},
"nonlocal":{
"value":[13.8009],
"error":[0],
"sigma":[15.1153]
},
"weight":{
"value":[0.99651],
"error":[0],
"sigma":[0.322993]
}
},
"independent points":inf,
"commments": [
"Warning: The estimated number of independent points is _greater_ that the points in the log file. Error bars are probably unreliable! "
]
}
<RS>
{
"warmup blocks":0,
"properties":{
"total_energy":{
"value":[-134.664],
"error":[0],
"sigma":[1.98012]
},
"kinetic":{
"value":[47.6819],
"error":[0],
"sigma":[12.4213]
},
"potential":{
"value":[-196.151],
"error":[0],
"sigma":[12.9315]
},
"nonlocal":{
"value":[13.8052],
"error":[0],
"sigma":[15.1237]
},
"weight":{
"value":[1.00152],
"error":[0],
"sigma":[0.322366]
}
},
"independent points":inf,
"commments": [
"Warning: The estimated number of independent points is _greater_ that the points in the log file. Error bars are probably unreliable! "
]
}
<RS>
