{
"warmup blocks":0,
"properties":{
"total_energy":{
"value":[-10.2857],
"error":[0],
"sigma":[0.386008]
},
"kinetic":{
"value":[3.02911],
"error":[0],
"sigma":[2.10719]
},
"potential":{
"value":[-14.636],
"error":[0],
"sigma":[2.37674]
},
"nonlocal":{
"value":[1.32117],
"error":[0],
"sigma":[2.54084]
},
"weight":{
"value":[1],
"error":[0],
"sigma":[0]
}
},
"independent points":inf,
"commments": [
"Warning: The estimated number of independent points is _greater_ that the points in the log file. Error bars are probably unreliable! "
]
}
<RS>
{
"warmup blocks":0,
"properties":{
"total_energy":{
"value":[-10.2868],
"error":[0],
"sigma":[0.50215]
},
"kinetic":{
"value":[3.00424],
"error":[0],
"sigma":[2.0599]
},
"potential":{
"value":[-14.6414],
"error":[0],
"sigma":[2.13696]
},
"nonlocal":{
"value":[1.35037],
"error":[0],
"sigma":[2.63999]
},
"weight":{
"value":[1],
"error":[0],
"sigma":[0]
}
},
"independent points":inf,
"commments": [
"Warning: The estimated number of independent points is _greater_ that the points in the log file. Error bars are probably unreliable! "
]
}
<RS>
{
"warmup blocks":0,
"properties":{
"total_energy":{
"value":[-10.2836],
"error":[0],
"sigma":[0.704262]
},
"kinetic":{
"value":[3.00913],
"error":[0],
"sigma":[2.08675]
},
"potential":{
"value":[-14.6208],
"error":[0],
"sigma":[2.15682]
},
"nonlocal":{
"value":[1.32806],
"error":[0],
"sigma":[2.55661]
},
"weight":{
"value":[1],
"error":[0],
"sigma":[0]
}
},
"independent points":inf,
"commments": [
"Warning: The estimated number of independent points is _greater_ that the points in the log file. Error bars are probably unreliable! "
]
}
<RS>
{
"warmup blocks":0,
"properties":{
"total_energy":{
"value":[-10.2859],
"error":[0],
"sigma":[0.377144]
},
"kinetic":{
"value":[3.01882],
"error":[0],
"sigma":[1.98532]
},
"potential":{
"value":[-14.6335],
"error":[0],
"sigma":[2.12645]
},
"nonlocal":{
"value":[1.32874],
"error":[0],
"sigma":[2.54906]
},
"weight":{
"value":[1],
"error":[0],
"sigma":[0]
}
},
"independent points":inf,
"commments": [
"Warning: The estimated number of independent points is _greater_ that the points in the log file. Error bars are probably unreliable! "
]
}
<RS>
{
"warmup blocks":0,
"properties":{
"total_energy":{
"value":[-10.2893],
"error":[0],
"sigma":[0.405069]
},
"kinetic":{
"value":[3.00804],
"error":[0],
"sigma":[2.00299]
},
"potential":{
"value":[-14.6172],
"error":[0],
"sigma":[2.11803]
},
"nonlocal":{
"value":[1.31986],
"error":[0],
"sigma":[2.53352]
},
"weight":{
"value":[1],
"error":[0],
"sigma":[0]
}
},
"independent points":inf,
"commments": [
"Warning: The estimated number of independent points is _greater_ that the points in the log file. Error bars are probably unreliable! "
]
}
<RS>
{
"warmup blocks":0,
"properties":{
"total_energy":{
"value":[-10.2873],
"error":[0],
"sigma":[0.65377]
},
"kinetic":{
"value":[3.00411],
"error":[0],
"sigma":[2.05917]
},
"potential":{
"value":[-14.6277],
"error":[0],
"sigma":[2.1293]
},
"nonlocal":{
"value":[1.3363],
"error":[0],
"sigma":[2.57457]
},
"weight":{
"value":[1],
"error":[0],
"sigma":[0]
}
},
"independent points":inf,
"commments": [
"Warning: The estimated number of independent points is _greater_ that the points in the log file. Error bars are probably unreliable! "
]
}
<RS>
{
"warmup blocks":0,
"properties":{
"total_energy":{
"value":[-10.2839],
"error":[0],
"sigma":[0.491059]
},
"kinetic":{
"value":[3.01544],
"error":[0],
"sigma":[1.95395]
},
"potential":{
"value":[-14.6372],
"error":[0],
"sigma":[2.13388]
},
"nonlocal":{
"value":[1.33787],
"error":[0],
"sigma":[2.54717]
},
"weight":{
"value":[1],
"error":[0],
"sigma":[0]
}
},
"independent points":inf,
"commments": [
"Warning: The estimated number of independent points is _greater_ that the points in the log file. Error bars are probably unreliable! "
]
}
<RS>
{
"warmup blocks":0,
"properties":{
"total_energy":{
"value":[-10.2847],
"error":[0],
"sigma":[0.724838]
},
"kinetic":{
"value":[3.00236],
"error":[0],
"sigma":[2.10904]
},
"potential":{
"value":[-14.6336],
"error":[0],
"sigma":[2.16506]
},
"nonlocal":{
"value":[1.34647],
"error":[0],
"sigma":[2.59606]
},
"weight":{
"value":[1],
"error":[0],
"sigma":[0]
}
},
"independent points":inf,
"commments": [
"Warning: The estimated number of independent points is _greater_ that the points in the log file. Error bars are probably unreliable! "
]
}
<RS>
{
"warmup blocks":0,
"properties":{
"total_energy":{
"value":[-10.2862],
"error":[0],
"sigma":[0.424583]
},
"kinetic":{
"value":[3.00978],
"error":[0],
"sigma":[1.97713]
},
"potential":{
"value":[-14.6215],
"error":[0],
"sigma":[2.1203]
},
"nonlocal":{
"value":[1.3256],
"error":[0],
"sigma":[2.54579]
},
"weight":{
"value":[1],
"error":[0],
"sigma":[0]
}
},
"independent points":inf,
"commments": [
"Warning: The estimated number of independent points is _greater_ that the points in the log file. Error bars are probably unreliable! "
]
}
<RS>
{
"warmup blocks":0,
"properties":{
"total_energy":{
"value":[-10.2819],
"error":[0],
"sigma":[0.9646]
},
"kinetic":{
"value":[3.0036],
"error":[0],
"sigma":[2.16131]
},
"potential":{
"value":[-14.6316],
"error":[0],
"sigma":[2.16103]
},
"nonlocal":{
"value":[1.34611],
"error":[0],
"sigma":[2.63601]
},
"weight":{
"value":[1],
"error":[0],
"sigma":[0]
}
},
"independent points":inf,
"commments": [
"Warning: The estimated number of independent points is _greater_ that the points in the log file. Error bars are probably unreliable! "
]
}
<RS>
{
"warmup blocks":0,
"properties":{
"total_energy":{
"value":[-10.2844],
"error":[0],
"sigma":[0.628691]
},
"kinetic":{
"value":[3.02064],
"error":[0],
"sigma":[2.00501]
},
"potential":{
"value":[-14.626],
"error":[0],
"sigma":[2.12726]
},
"nonlocal":{
"value":[1.32095],
"error":[0],
"sigma":[2.53991]
},
"weight":{
"value":[1],
"error":[0],
"sigma":[0]
}
},
"independent points":inf,
"commments": [
"Warning: The estimated number of independent points is _greater_ that the points in the log file. Error bars are probably unreliable! "
]
}
<RS>
{
"warmup blocks":0,
"properties":{
"total_energy":{
"value":[-10.2863],
"error":[0],
"sigma":[0.346622]
},
"kinetic":{
"value":[3.03611],
"error":[0],
"sigma":[1.91458]
},
"potential":{
"value":[-14.6309],
"error":[0],
"sigma":[2.11688]
},
"nonlocal":{
"value":[1.3085],
"error":[0],
"sigma":[2.45228]
},
"weight":{
"value":[1],
"error":[0],
"sigma":[0]
}
},
"independent points":inf,
"commments": [
"Warning: The estimated number of independent points is _greater_ that the points in the log file. Error bars are probably unreliable! "
]
}
<RS>
{
"warmup blocks":0,
"properties":{
"total_energy":{
"value":[-10.2826],
"error":[0],
"sigma":[0.572662]
},
"kinetic":{
"value":[3.01667],
"error":[0],
"sigma":[1.97611]
},
"potential":{
"value":[-14.6305],
"error":[0],
"sigma":[2.12765]
},
"nonlocal":{
"value":[1.33127],
"error":[0],
"sigma":[2.5469]
},
"weight":{
"value":[1],
"error":[0],
"sigma":[0]
}
},
"independent points":inf,
"commments": [
"Warning: The estimated number of independent points is _greater_ that the points in the log file. Error bars are probably unreliable! "
]
}
<RS>
{
"warmup blocks":0,
"properties":{
"total_energy":{
"value":[-10.2854],
"error":[0],
"sigma":[0.420162]
},
"kinetic":{
"value":[3.01933],
"error":[0],
"sigma":[2.00535]
},
"potential":{
"value":[-14.6265],
"error":[0],
"sigma":[2.12361]
},
"nonlocal":{
"value":[1.32177],
"error":[0],
"sigma":[2.55027]
},
"weight":{
"value":[1],
"error":[0],
"sigma":[0]
}
},
"independent points":inf,
"commments": [
"Warning: The estimated number of independent points is _greater_ that the points in the log file. Error bars are probably unreliable! "
]
}
<RS>
{
"warmup blocks":0,
"properties":{
"total_energy":{
"value":[-10.2841],
"error":[0],
"sigma":[0.827077]
},
"kinetic":{
"value":[3.01515],
"error":[0],
"sigma":[2.09815]
},
"potential":{
"value":[-14.6335],
"error":[0],
"sigma":[2.15087]
},
"nonlocal":{
"value":[1.33431],
"error":[0],
"sigma":[2.59184]
},
"weight":{
"value":[1],
"error":[0],
"sigma":[0]
}
},
"independent points":inf,
"commments": [
"Warning: The estimated number of independent points is _greater_ that the points in the log file. Error bars are probably unreliable! "
]
}
<RS>
{
"warmup blocks":0,
"properties":{
"total_energy":{
"value":[-10.2876],
"error":[0],
"sigma":[0.461561]
},
"kinetic":{
"value":[3.01897],
"error":[0],
"sigma":[2.01244]
},
"potential":{
"value":[-14.6319],
"error":[0],
"sigma":[2.12623]
},
"nonlocal":{
"value":[1.3254],
"error":[0],
"sigma":[2.54581]
},
"weight":{
"value":[1],
"error":[0],
"sigma":[0]
}
},
"independent points":inf,
"commments": [
"Warning: The estimated number of independent points is _greater_ that the points in the log file. Error bars are probably unreliable! "
]
}
<RS>
{
"warmup blocks":0,
"properties":{
"total_energy":{
"value":[-10.2846],
"error":[0],
"sigma":[0.497901]
},
"kinetic":{
"value":[3.00187],
"error":[0],
"sigma":[2.02753]
},
"potential":{
"value":[-14.6183],
"error":[0],
"sigma":[2.12739]
},
"nonlocal":{
"value":[1.33184],
"error":[0],
"sigma":[2.58983]
},
"weight":{
"value":[1],
"error":[0],
"sigma":[0]
}
},
"independent points":inf,
"commments": [
"Warning: The estimated number of independent points is _greater_ that the points in the log file. Error bars are probably unreliable! "
]
}
<RS>
{
"warmup blocks":0,
"properties":{
"total_energy":{
"value":[-10.2879],
"error":[0],
"sigma":[0.839056]
},
"kinetic":{
"value":[3.00887],
"error":[0],
"sigma":[2.19066]
},
"potential":{
"value":[-14.6391],
"error":[0],
"sigma":[2.16121]
},
"nonlocal":{
"value":[1.34233],
"error":[0],
"sigma":[2.56174]
},
"weight":{
"value":[1],
"error":[0],
"sigma":[0]
}
},
"independent points":inf,
"commments": [
"Warning: The estimated number of independent points is _greater_ that the points in the log file. Error bars are probably unreliable! "
]
}
<RS>
{
"warmup blocks":0,
"properties":{
"total_energy":{
"value":[-10.2857],
"error":[0],
"sigma":[0.499294]
},
"kinetic":{
"value":[3.02083],
"error":[0],
"sigma":[2.01918]
},
"potential":{
"value":[-14.629],
"error":[0],
"sigma":[2.12532]
},
"nonlocal":{
"value":[1.32244],
"error":[0],
"sigma":[2.55357]
},
"weight":{
"value":[1],
"error":[0],
"sigma":[0]
}
},
"independent points":inf,
"commments": [
"Warning: The estimated number of independent points is _greater_ that the points in the log file. Error bars are probably unreliable! "
]
}
<RS>
{
"warmup blocks":0,
"properties":{
"total_energy":{
"value":[-10.2855],
"error":[0],
"sigma":[0.457235]
},
"kinetic":{
"value":[3.01995],
"error":[0],
"sigma":[1.97394]
},
"potential":{
"value":[-14.6277],
"error":[0],
"sigma":[2.11649]
},
"nonlocal":{
"value":[1.32225],
"error":[0],
"sigma":[2.53202]
},
"weight":{
"value":[1],
"error":[0],
"sigma":[0]
}
},
"independent points":inf,
"commments": [
"Warning: The estimated number of independent points is _greater_ that the points in the log file. Error bars are probably unreliable! "
]
}
<RS>
