{
"warmup blocks":0,
"properties":{
"total_energy":{
"value":[-66.9572],
"error":[0],
"sigma":[0.696821]
},
"kinetic":{
"value":[22.9235],
"error":[0],
"sigma":[8.7323]
},
"potential":{
"value":[-96.4482],
"error":[0],
"sigma":[9.10477]
},
"nonlocal":{
"value":[6.56741],
"error":[0],
"sigma":[10.6418]
},
"weight":{
"value":[1.02617],
"error":[0],
"sigma":[0.115927]
}
},
"independent points":inf,
"commments": [
"Warning: The estimated number of independent points is _greater_ that the points in the log file. Error bars are probably unreliable! "
]
}
<RS>
{
"warmup blocks":0,
"properties":{
"total_energy":{
"value":[-66.9219],
"error":[0],
"sigma":[0.709747]
},
"kinetic":{
"value":[23.0474],
"error":[0],
"sigma":[8.71278]
},
"potential":{
"value":[-96.5698],
"error":[0],
"sigma":[9.14263]
},
"nonlocal":{
"value":[6.60054],
"error":[0],
"sigma":[10.6204]
},
"weight":{
"value":[1.01094],
"error":[0],
"sigma":[0.21529]
}
},
"independent points":inf,
"commments": [
"Warning: The estimated number of independent points is _greater_ that the points in the log file. Error bars are probably unreliable! "
]
}
<RS>
{
"warmup blocks":0,
"properties":{
"total_energy":{
"value":[-66.913],
"error":[0],
"sigma":[0.71704]
},
"kinetic":{
"value":[23.1191],
"error":[0],
"sigma":[8.70307]
},
"potential":{
"value":[-96.6651],
"error":[0],
"sigma":[9.14535]
},
"nonlocal":{
"value":[6.63296],
"error":[0],
"sigma":[10.6751]
},
"weight":{
"value":[0.9843],
"error":[0],
"sigma":[0.265704]
}
},
"independent points":inf,
"commments": [
"Warning: The estimated number of independent points is _greater_ that the points in the log file. Error bars are probably unreliable! "
]
}
<RS>
{
"warmup blocks":0,
"properties":{
"total_energy":{
"value":[-66.9058],
"error":[0],
"sigma":[0.722076]
},
"kinetic":{
"value":[23.1215],
"error":[0],
"sigma":[8.74394]
},
"potential":{
"value":[-96.6766],
"error":[0],
"sigma":[9.1779]
},
"nonlocal":{
"value":[6.64929],
"error":[0],
"sigma":[10.6637]
},
"weight":{
"value":[0.978068],
"error":[0],
"sigma":[0.286889]
}
},
"independent points":inf,
"commments": [
"Warning: The estimated number of independent points is _greater_ that the points in the log file. Error bars are probably unreliable! "
]
}
<RS>
{
"warmup blocks":0,
"properties":{
"total_energy":{
"value":[-66.9086],
"error":[0],
"sigma":[0.713868]
},
"kinetic":{
"value":[23.1534],
"error":[0],
"sigma":[8.70948]
},
"potential":{
"value":[-96.6541],
"error":[0],
"sigma":[9.16659]
},
"nonlocal":{
"value":[6.59208],
"error":[0],
"sigma":[10.6661]
},
"weight":{
"value":[0.980138],
"error":[0],
"sigma":[0.292503]
}
},
"independent points":inf,
"commments": [
"Warning: The estimated number of independent points is _greater_ that the points in the log file. Error bars are probably unreliable! "
]
}
<RS>
{
"warmup blocks":0,
"properties":{
"total_energy":{
"value":[-66.9051],
"error":[0],
"sigma":[0.717918]
},
"kinetic":{
"value":[23.1572],
"error":[0],
"sigma":[8.73548]
},
"potential":{
"value":[-96.6727],
"error":[0],
"sigma":[9.0886]
},
"nonlocal":{
"value":[6.61038],
"error":[0],
"sigma":[10.6658]
},
"weight":{
"value":[0.981135],
"error":[0],
"sigma":[0.296934]
}
},
"independent points":inf,
"commments": [
"Warning: The estimated number of independent points is _greater_ that the points in the log file. Error bars are probably unreliable! "
]
}
<RS>
{
"warmup blocks":0,
"properties":{
"total_energy":{
"value":[-66.9048],
"error":[0],
"sigma":[0.714136]
},
"kinetic":{
"value":[23.0887],
"error":[0],
"sigma":[8.7013]
},
"potential":{
"value":[-96.5514],
"error":[0],
"sigma":[9.06939]
},
"nonlocal":{
"value":[6.55795],
"error":[0],
"sigma":[10.6511]
},
"weight":{
"value":[0.987588],
"error":[0],
"sigma":[0.30017]
}
},
"independent points":inf,
"commments": [
"Warning: The estimated number of independent points is _greater_ that the points in the log file. Error bars are probably unreliable! "
]
}
<RS>
{
"warmup blocks":0,
"properties":{
"total_energy":{
"value":[-66.9064],
"error":[0],
"sigma":[0.719678]
},
"kinetic":{
"value":[23.0246],
"error":[0],
"sigma":[8.8114]
},
"potential":{
"value":[-96.574],
"error":[0],
"sigma":[9.12052]
},
"nonlocal":{
"value":[6.64308],
"error":[0],
"sigma":[10.7813]
},
"weight":{
"value":[0.994036],
"error":[0],
"sigma":[0.305687]
}
},
"independent points":inf,
"commments": [
"Warning: The estimated number of independent points is _greater_ that the points in the log file. Error bars are probably unreliable! "
]
}
<RS>
{
"warmup blocks":0,
"properties":{
"total_energy":{
"value":[-66.9042],
"error":[0],
"sigma":[0.716346]
},
"kinetic":{
"value":[23.0794],
"error":[0],
"sigma":[8.66132]
},
"potential":{
"value":[-96.5939],
"error":[0],
"sigma":[9.11972]
},
"nonlocal":{
"value":[6.61036],
"error":[0],
"sigma":[10.6183]
},
"weight":{
"value":[0.995574],
"error":[0],
"sigma":[0.305688]
}
},
"independent points":inf,
"commments": [
"Warning: The estimated number of independent points is _greater_ that the points in the log file. Error bars are probably unreliable! "
]
}
<RS>
{
"warmup blocks":0,
"properties":{
"total_energy":{
"value":[-66.9024],
"error":[0],
"sigma":[0.726476]
},
"kinetic":{
"value":[23.2139],
"error":[0],
"sigma":[8.67467]
},
"potential":{
"value":[-96.7094],
"error":[0],
"sigma":[9.08568]
},
"nonlocal":{
"value":[6.59304],
"error":[0],
"sigma":[10.6613]
},
"weight":{
"value":[0.995799],
"error":[0],
"sigma":[0.304622]
}
},
"independent points":inf,
"commments": [
"Warning: The estimated number of independent points is _greater_ that the points in the log file. Error bars are probably unreliable! "
]
}
<RS>
{
"warmup blocks":0,
"properties":{
"total_energy":{
"value":[-66.9041],
"error":[0],
"sigma":[0.716716]
},
"kinetic":{
"value":[23.242],
"error":[0],
"sigma":[8.69721]
},
"potential":{
"value":[-96.857],
"error":[0],
"sigma":[9.11984]
},
"nonlocal":{
"value":[6.71088],
"error":[0],
"sigma":[10.682]
},
"weight":{
"value":[0.996411],
"error":[0],
"sigma":[0.300683]
}
},
"independent points":inf,
"commments": [
"Warning: The estimated number of independent points is _greater_ that the points in the log file. Error bars are probably unreliable! "
]
}
<RS>
{
"warmup blocks":0,
"properties":{
"total_energy":{
"value":[-66.9069],
"error":[0],
"sigma":[0.715467]
},
"kinetic":{
"value":[23.2403],
"error":[0],
"sigma":[8.67335]
},
"potential":{
"value":[-96.7319],
"error":[0],
"sigma":[8.99548]
},
"nonlocal":{
"value":[6.5847],
"error":[0],
"sigma":[10.6351]
},
"weight":{
"value":[0.998728],
"error":[0],
"sigma":[0.299526]
}
},
"independent points":inf,
"commments": [
"Warning: The estimated number of independent points is _greater_ that the points in the log file. Error bars are probably unreliable! "
]
}
<RS>
{
"warmup blocks":0,
"properties":{
"total_energy":{
"value":[-66.9054],
"error":[0],
"sigma":[0.714894]
},
"kinetic":{
"value":[23.0145],
"error":[0],
"sigma":[8.73956]
},
"potential":{
"value":[-96.5607],
"error":[0],
"sigma":[9.1167]
},
"nonlocal":{
"value":[6.64085],
"error":[0],
"sigma":[10.7344]
},
"weight":{
"value":[0.999095],
"error":[0],
"sigma":[0.300936]
}
},
"independent points":inf,
"commments": [
"Warning: The estimated number of independent points is _greater_ that the points in the log file. Error bars are probably unreliable! "
]
}
<RS>
{
"warmup blocks":0,
"properties":{
"total_energy":{
"value":[-66.8969],
"error":[0],
"sigma":[0.720225]
},
"kinetic":{
"value":[23.1032],
"error":[0],
"sigma":[8.74384]
},
"potential":{
"value":[-96.6826],
"error":[0],
"sigma":[9.1938]
},
"nonlocal":{
"value":[6.68251],
"error":[0],
"sigma":[10.7525]
},
"weight":{
"value":[0.996337],
"error":[0],
"sigma":[0.300991]
}
},
"independent points":inf,
"commments": [
"Warning: The estimated number of independent points is _greater_ that the points in the log file. Error bars are probably unreliable! "
]
}
<RS>
{
"warmup blocks":0,
"properties":{
"total_energy":{
"value":[-66.9025],
"error":[0],
"sigma":[0.71371]
},
"kinetic":{
"value":[23.1305],
"error":[0],
"sigma":[8.75645]
},
"potential":{
"value":[-96.6156],
"error":[0],
"sigma":[9.1028]
},
"nonlocal":{
"value":[6.58258],
"error":[0],
"sigma":[10.7048]
},
"weight":{
"value":[0.995597],
"error":[0],
"sigma":[0.304253]
}
},
"independent points":inf,
"commments": [
"Warning: The estimated number of independent points is _greater_ that the points in the log file. Error bars are probably unreliable! "
]
}
<RS>
{
"warmup blocks":0,
"properties":{
"total_energy":{
"value":[-66.8988],
"error":[0],
"sigma":[0.724445]
},
"kinetic":{
"value":[23.2089],
"error":[0],
"sigma":[8.8429]
},
"potential":{
"value":[-96.8418],
"error":[0],
"sigma":[9.18162]
},
"nonlocal":{
"value":[6.73417],
"error":[0],
"sigma":[10.8173]
},
"weight":{
"value":[0.995323],
"error":[0],
"sigma":[0.306372]
}
},
"independent points":inf,
"commments": [
"Warning: The estimated number of independent points is _greater_ that the points in the log file. Error bars are probably unreliable! "
]
}
<RS>
{
"warmup blocks":0,
"properties":{
"total_energy":{
"value":[-66.9034],
"error":[0],
"sigma":[0.718707]
},
"kinetic":{
"value":[23.3132],
"error":[0],
"sigma":[8.74453]
},
"potential":{
"value":[-96.8941],
"error":[0],
"sigma":[9.1851]
},
"nonlocal":{
"value":[6.67742],
"error":[0],
"sigma":[10.6862]
},
"weight":{
"value":[0.99655],
"error":[0],
"sigma":[0.309255]
}
},
"independent points":inf,
"commments": [
"Warning: The estimated number of independent points is _greater_ that the points in the log file. Error bars are probably unreliable! "
]
}
<RS>
{
"warmup blocks":0,
"properties":{
"total_energy":{
"value":[-66.9077],
"error":[0],
"sigma":[0.753505]
},
"kinetic":{
"value":[23.1585],
"error":[0],
"sigma":[8.7421]
},
"potential":{
"value":[-96.774],
"error":[0],
"sigma":[9.08241]
},
"nonlocal":{
"value":[6.70776],
"error":[0],
"sigma":[10.7716]
},
"weight":{
"value":[0.999822],
"error":[0],
"sigma":[0.309558]
}
},
"independent points":inf,
"commments": [
"Warning: The estimated number of independent points is _greater_ that the points in the log file. Error bars are probably unreliable! "
]
}
<RS>
{
"warmup blocks":0,
"properties":{
"total_energy":{
"value":[-66.9072],
"error":[0],
"sigma":[0.717884]
},
"kinetic":{
"value":[23.2252],
"error":[0],
"sigma":[8.70448]
},
"potential":{
"value":[-96.7664],
"error":[0],
"sigma":[9.11179]
},
"nonlocal":{
"value":[6.63402],
"error":[0],
"sigma":[10.6533]
},
"weight":{
"value":[1.00047],
"error":[0],
"sigma":[0.305391]
}
},
"independent points":inf,
"commments": [
"Warning: The estimated number of independent points is _greater_ that the points in the log file. Error bars are probably unreliable! "
]
}
<RS>
{
"warmup blocks":0,
"properties":{
"total_energy":{
"value":[-66.9062],
"error":[0],
"sigma":[0.711315]
},
"kinetic":{
"value":[23.2356],
"error":[0],
"sigma":[8.63176]
},
"potential":{
"value":[-96.7583],
"error":[0],
"sigma":[9.08724]
},
"nonlocal":{
"value":[6.61645],
"error":[0],
"sigma":[10.5839]
},
"weight":{
"value":[1.00283],
"error":[0],
"sigma":[0.303839]
}
},
"independent points":inf,
"commments": [
"Warning: The estimated number of independent points is _greater_ that the points in the log file. Error bars are probably unreliable! "
]
}
<RS>
{
"warmup blocks":0,
"properties":{
"total_energy":{
"value":[-66.8997],
"error":[0],
"sigma":[0.718127]
},
"kinetic":{
"value":[23.1833],
"error":[0],
"sigma":[8.7417]
},
"potential":{
"value":[-96.7295],
"error":[0],
"sigma":[9.16348]
},
"nonlocal":{
"value":[6.64643],
"error":[0],
"sigma":[10.7295]
},
"weight":{
"value":[0.998339],
"error":[0],
"sigma":[0.302443]
}
},
"independent points":inf,
"commments": [
"Warning: The estimated number of independent points is _greater_ that the points in the log file. Error bars are probably unreliable! "
]
}
<RS>
{
"warmup blocks":0,
"properties":{
"total_energy":{
"value":[-66.9032],
"error":[0],
"sigma":[0.715638]
},
"kinetic":{
"value":[23.0652],
"error":[0],
"sigma":[8.79744]
},
"potential":{
"value":[-96.5918],
"error":[0],
"sigma":[9.13206]
},
"nonlocal":{
"value":[6.62342],
"error":[0],
"sigma":[10.7999]
},
"weight":{
"value":[0.99727],
"error":[0],
"sigma":[0.307811]
}
},
"independent points":inf,
"commments": [
"Warning: The estimated number of independent points is _greater_ that the points in the log file. Error bars are probably unreliable! "
]
}
<RS>
{
"warmup blocks":0,
"properties":{
"total_energy":{
"value":[-66.9022],
"error":[0],
"sigma":[0.712417]
},
"kinetic":{
"value":[23.1639],
"error":[0],
"sigma":[8.6929]
},
"potential":{
"value":[-96.6894],
"error":[0],
"sigma":[9.12411]
},
"nonlocal":{
"value":[6.62322],
"error":[0],
"sigma":[10.6515]
},
"weight":{
"value":[0.997835],
"error":[0],
"sigma":[0.303064]
}
},
"independent points":inf,
"commments": [
"Warning: The estimated number of independent points is _greater_ that the points in the log file. Error bars are probably unreliable! "
]
}
<RS>
{
"warmup blocks":0,
"properties":{
"total_energy":{
"value":[-66.9053],
"error":[0],
"sigma":[0.720339]
},
"kinetic":{
"value":[23.118],
"error":[0],
"sigma":[8.77284]
},
"potential":{
"value":[-96.647],
"error":[0],
"sigma":[9.12313]
},
"nonlocal":{
"value":[6.62367],
"error":[0],
"sigma":[10.7761]
},
"weight":{
"value":[0.999191],
"error":[0],
"sigma":[0.300117]
}
},
"independent points":inf,
"commments": [
"Warning: The estimated number of independent points is _greater_ that the points in the log file. Error bars are probably unreliable! "
]
}
<RS>
{
"warmup blocks":0,
"properties":{
"total_energy":{
"value":[-66.9014],
"error":[0],
"sigma":[0.716793]
},
"kinetic":{
"value":[23.1252],
"error":[0],
"sigma":[8.714]
},
"potential":{
"value":[-96.6633],
"error":[0],
"sigma":[9.10098]
},
"nonlocal":{
"value":[6.63663],
"error":[0],
"sigma":[10.5783]
},
"weight":{
"value":[0.999195],
"error":[0],
"sigma":[0.299568]
}
},
"independent points":inf,
"commments": [
"Warning: The estimated number of independent points is _greater_ that the points in the log file. Error bars are probably unreliable! "
]
}
<RS>
